pyveda/__init__.py
pyveda/auth.py
pyveda/config.py
pyveda/exceptions.py
pyveda/main.py
pyveda/utils.py
pyveda/frameworks/__init__.py
pyveda/frameworks/batch_generator.py
pyveda/frameworks/transforms.py
pyveda/io/__init__.py
pyveda/io/io.py
pyveda/io/utils.py
pyveda/io/hdf5/__init__.py
pyveda/io/hdf5/serializers.py
pyveda/io/remote/__init__.py
pyveda/io/remote/client.py
pyveda/io/remote/handlers.py
pyveda/models/__init__.py
pyveda/models/main.py
pyveda/vedaset/__init__.py
pyveda/vedaset/abstract.py
pyveda/vedaset/base.py
pyveda/vedaset/interface.py
pyveda/vedaset/props.py
pyveda/vedaset/utils.py
pyveda/vedaset/vedaset.py
pyveda/vedaset/store/__init__.py
pyveda/vedaset/store/vedabase.py
pyveda/vedaset/stream/__init__.py
pyveda/vedaset/stream/vedastream.py
pyveda/vedaset/veda/__init__.py
pyveda/vedaset/veda/api.py
pyveda/vedaset/veda/loaders.py
pyveda/vedaset/veda/props.py
pyveda/vedaset/veda/rda.py
pyveda/vv/__init__.py
pyveda/vv/labelizer.py
pyveda-0.0.7.dist-info/METADATA
pyveda-0.0.7.dist-info/WHEEL
pyveda-0.0.7.dist-info/top_level.txt
pyveda-0.0.7.dist-info/RECORD
